README.md
setup.py
gurd/LDC2013T21.py
gurd/__init__.py
sacfrwe.egg-info/PKG-INFO
sacfrwe.egg-info/SOURCES.txt
sacfrwe.egg-info/dependency_links.txt
sacfrwe.egg-info/top_level.txt