Metadata-Version: 1.0
Name: sacfrwe
Version: 0.0.2
Summary: just a simple toudu
Home-page: ['https://github.com/ewrfcas/pip_toudu/tree/master']
Author: jcc
Author-email: sacfrwe@126.com
License: MIT License
Keywords: simple,test
Platform: any
